mixbox.py
pymixbox-2.0.0.dist-info/LICENSE
pymixbox-2.0.0.dist-info/METADATA
pymixbox-2.0.0.dist-info/WHEEL
pymixbox-2.0.0.dist-info/top_level.txt
pymixbox-2.0.0.dist-info/RECORD
