Metadata-Version: 2.1
Name: pymixbox
Version: 2.0.0
Summary: Pigment-Based Color Mixing
Author: Secret Weapons
Author-email: mixbox@scrtwpns.com
License: CC-BY-NC-4.0
Project-URL: homepage, https://scrtwpns.com/mixbox
Project-URL: repository, https://github.com/scrtwpns/mixbox
Keywords: color mixing,pigments,rgb,kubelka munk,paints,paint mixing,graphics
License-File: LICENSE
